mozfederatedpolicybuilder/__init__.py
mozfederatedpolicybuilder-0.1.0.dist-info/METADATA
mozfederatedpolicybuilder-0.1.0.dist-info/WHEEL
mozfederatedpolicybuilder-0.1.0.dist-info/entry_points.txt
mozfederatedpolicybuilder-0.1.0.dist-info/top_level.txt
mozfederatedpolicybuilder-0.1.0.dist-info/RECORD
