Metadata-Version: 2.1
Name: mozfederatedpolicybuilder
Version: 0.1.0
Summary: Tool to create an AWS IAM Role with a federated policy allowing users to login with Single Sign On
Home-page: https://github.com/mozilla-iam/mozfederatedpolicybuilder
Author: Gene Wood
Author-email: gene_wood@cementhorizon.com
License: UNKNOWN
Platform: UNKNOWN
Classifier: Development Status :: 3 - Alpha
Classifier: Environment :: Console
Classifier: Intended Audience :: Developers
Classifier: Programming Language :: Python :: 2
Classifier: Programming Language :: Python :: 3
Classifier: License :: OSI Approved :: Mozilla Public License 2.0 (MPL 2.0)
Classifier: Operating System :: OS Independent
Classifier: Topic :: Software Development :: Code Generators
Requires-Dist: PyYAML
Provides-Extra: test
Requires-Dist: pytest ; extra == 'test'
Requires-Dist: pytest-cov ; extra == 'test'
Requires-Dist: pytest-clarity ; extra == 'test'
Requires-Dist: mock ; (python_version < "3.3") and extra == 'test'
